Lab5/ALU.v
/*
CO225 Lab 05 (part 5)
Authors : E/19/105 FAHMAN M.H.M.
          E/19/106 FASEEH M.F.M.
*/

//ALU module
module alu(DATA1, DATA2, RESULT, SELECT, ZERO, SHIFTINDICATOR);
    //Port declarations
    input [7:0] DATA1, DATA2;   //8 bit inputs
    input [2:0] SELECT;         //3 bit input
    input SHIFTINDICATOR;       //1 bit input (indicator for sll & srl)
    output reg ZERO;                //1 bit output (indicator for beq) 
    output reg [7:0] RESULT;    //8 bit output
    wire [7:0] Fwd,Add,And,Or,LogicalShift,ArithmeticShift,Rotate;  //8 bit temporary variables
    output reg zero_flag;       //to check invalid OP code

    /*
    perform all operations and get results of each
    operation by instantiating lower level modules
    */
    FORWARD Forward_(DATA2, Fwd);
    ADD Add_(DATA1, DATA2, Add);
    AND And_(DATA1, DATA2, And);
    OR Or_(DATA1, DATA2, Or);
    LOGICALSHIFT LogicalShift_(DATA1, DATA2, SHIFTINDICATOR, LogicalShift);
    ARITHMETICSHIFT ArithmeticShift_(DATA1, DATA2, ArithmeticShift);
    ROTATE Rotate_(DATA1, DATA2, Rotate);

    /*Check whether the result of substraction operation is zero or not,
      in order to implement the beq instruction
    */
    always @(*) begin
        if (Add==0) begin
            ZERO=1;
        end else begin
            ZERO=0;
        end
        
    end
    

    /*
    According to the OP code 
    switch the appropriate value to the result
    using MUX
    */
    always @(*)
    begin
        zero_flag = 1'b0;       //initialize to 0

        case (SELECT)
            3'b000:  RESULT = Fwd;
            3'b001:  RESULT = Add;
            3'b010:  RESULT = And;
            3'b011:  RESULT = Or;
            3'b100:  RESULT = LogicalShift;
            3'b101:  RESULT = ArithmeticShift;
            3'b110:  RESULT = Rotate;
            default: zero_flag = 1'b1;  //value to 1
        endcase 
        /*Check for invalid P code.
        if invalid OP code is detected, terminate the program
        */
        if (zero_flag == 1) begin
            $display("Invalid OP code..");
            $finish;
        end
    end
endmodule
/*
----------Lower level modules-----------
*/
//FORWARD module
module FORWARD(DATA2, RESULT);
    //Port declarations
    input [7:0] DATA2;
    output reg [7:0] RESULT;
    
    always @(DATA2)
    begin
        #1 RESULT = DATA2;
    end 
endmodule

//ADD module
module ADD(DATA1, DATA2, RESULT);
    //Port declarations
    input [7:0] DATA1, DATA2;
    output reg [7:0] RESULT;

    always @(DATA1, DATA2)
    begin
        #2 RESULT = DATA1 + DATA2;
    end
endmodule

//AND module
module AND(DATA1, DATA2, RESULT);
   //Port declarations
    input [7:0] DATA1, DATA2;
    output reg [7:0] RESULT;

    always @(DATA1, DATA2)
    begin
        #1 RESULT = DATA1 & DATA2;
    end
endmodule

//OR module
module OR(DATA1, DATA2, RESULT);
   //Port declarations
    input [7:0] DATA1, DATA2;
    output reg [7:0] RESULT;

    always @(DATA1, DATA2)
    begin
        #1 RESULT = DATA1 | DATA2;
    end
endmodule

//Logical Shift module
module LOGICALSHIFT (OPERAND, SHIFTAMOUNT, SHIFTSIDE, RESULT);
    //Port declarations
    input [7:0] OPERAND, SHIFTAMOUNT;
    input SHIFTSIDE;                    //If 0 leftshift, if 1 rightshift
    output reg [7:0] RESULT;
    reg [7:0] tempOperand;              //temporary register
    reg [6:0] temp;                     //temporary register
    integer i;                          //for looping

    always @(SHIFTAMOUNT, OPERAND) begin
        #1
        tempOperand = OPERAND;
        for (i = 1; i<=SHIFTAMOUNT; i++ ) begin
            if (SHIFTSIDE == 0) begin       //Leftshift operation
                temp = tempOperand[6:0];
                RESULT[7:1] = temp;
                RESULT[0] = 1'b0;
                tempOperand = RESULT;
            end else begin                  //Rightshift operation
                temp = tempOperand[7:1];
                RESULT[6:0] = temp;
                RESULT[7] = 1'b0;
                tempOperand = RESULT;
            end
        end
    end
endmodule

//Arithmetic Shift module
module ARITHMETICSHIFT(OPERAND, SHIFTAMOUNT, RESULT);
    //Port declarations
    input [7:0] OPERAND, SHIFTAMOUNT;
    output reg [7:0] RESULT;
    reg [7:0] tempOperand;          //temporary register 
    reg [6:0] temp;                 //temporary register
    integer j;                      //for looping

    always @(OPERAND, SHIFTAMOUNT) begin
        #1
        tempOperand = OPERAND;
        for (j = 1; j<=SHIFTAMOUNT ; j++) begin
            if (tempOperand[7]==1'b0) begin     //If MSB is 0 add leading zeros
                temp = tempOperand[7:1];
                RESULT[6:0] = temp;
                RESULT[7] = 1'b0;
                tempOperand = RESULT;
            end else begin                      //If MSB is 1 add leading ones
                temp = tempOperand[7:1];
                RESULT[6:0] = temp;
                RESULT[7] = 1'b1;
                tempOperand = RESULT;
            end
        end
    end
endmodule

//Rotate right module
module ROTATE(OPERAND, ROTATEAMOUNT, RESULT);
    input [7:0] OPERAND, ROTATEAMOUNT;
    output reg [7:0] RESULT;
    reg tempLSB;                    //temporary register
    reg [6:0] temp;                 //temporary register
    reg [7:0] tempOperand;          //temporary register
    integer k;                      //for looping

    always @(OPERAND, ROTATEAMOUNT) begin
        #1
        tempOperand = OPERAND;      
        tempLSB = OPERAND[0];       //Save the LSB 

        //ROtate through a loop
        for ( k=1 ; k<=ROTATEAMOUNT ; k++) begin 
            temp = tempOperand[7:1];        
            RESULT[6:0] = temp;
            RESULT[7] = tempLSB;
            tempOperand = RESULT;
            tempLSB = RESULT[0];
        end
    end
endmodule

Lab5/group19_lab5_part5/Reg_file.v
/*
CO225 Lab 05 (part 5)
Authors : E/19/105 FAHMAN M.H.M.
          E/19/106 FASEEH M.F.M.
*/

//Reg_File module
module reg_file(IN,OUT1,OUT2,INADDRESS,OUT1ADDRESS,OUT2ADDRESS,WRITE,CLK,RESET);
    
    //Port declarations
    input wire [7:0] IN;        //8 bit input
    input [2:0] INADDRESS, OUT1ADDRESS, OUT2ADDRESS;    //3 bit address inputs
    input WRITE, CLK, RESET;    //1 bit inputs
    output [7:0] OUT1, OUT2;    //8 bit outputs
    
    //register array
    reg [7:0] register [7:0]; 

    integer i;  //declared for looping   

    always @(posedge CLK)   //When rising edge of clock
    begin 
        if (WRITE == 1) begin   //When WRITE is in high
            //Write IN to the given memory address
            case (INADDRESS)
                3'b000 :  register[0] <= #1 IN;
                3'b001 :  register[1] <= #1 IN;
                3'b010 :  register[2] <= #1 IN;
                3'b011 :  register[3] <= #1 IN;
                3'b100 :  register[4] <= #1 IN;
                3'b101 :  register[5] <= #1 IN;
                3'b110 :  register[6] <= #1 IN;
                3'b111 :  register[7] <= #1 IN;
            endcase

            /*
            //Alternate
            #1 register[INADDRESS] = IN;
            */
        end

        if (RESET == 1) begin   //When RESET is in high
            
            #1  for (i=0 ; i<8 ; i++)
                begin
                    register[i] = 8'b00000000;  //WRITE all memory zero
                end
        end
    end

    //READ two parallel data outputs
    assign #2 OUT1 = register[OUT1ADDRESS];
    assign #2 OUT2 = register[OUT2ADDRESS];
endmodule

Lab5/CPU.v
/*
CO225 Lab 05 (part 5)
Authors : E/19/105 FAHMAN M.H.M.
          E/19/106 FASEEH M.F.M.
*/
`include "ALU.V"            //Import ALU module
`include "Reg_file.v"       //Import Reg_file module


//Testbench for cpu module
module cpu_tb;
    reg CLK, RESET;
    wire [31:0] PC;
    reg [31:0] INSTRUCTION;
    /* 
    ------------------------
     SIMPLE INSTRUCTION MEM
    ------------------------
    */
    
    // TODO: Initialize an array of registers (8x1024) named 'instr_mem' to be used as instruction memory
    

    reg [7:0] instr_mem[0:1023];
  
    // TODO: Create combinational logic to support CPU instruction fetching, given the Program Counter(PC) value 
    //       (make sure you include the delay for instruction fetching here)

    always @(PC) begin
        #2
        INSTRUCTION = {instr_mem[PC+3], instr_mem[PC+2], instr_mem[PC+1], instr_mem[PC]};
    end
    
    initial
    begin
        // Initialize instruction memory with the set of instructions you need execute on CPU
        
        // manually loading instructions to instr_mem
        
        {instr_mem[10'd3], instr_mem[10'd2], instr_mem[10'd1], instr_mem[10'd0]}        = 32'b00000000_00000000_00000000_00001001;  //loadi 0     #9
        {instr_mem[10'd7], instr_mem[10'd6], instr_mem[10'd5], instr_mem[10'd4]}        = 32'b00000110_00000001_00000000_00000000;  //j     #1     
        {instr_mem[10'd11], instr_mem[10'd10], instr_mem[10'd9], instr_mem[10'd8]}      = 32'b00000000_00000001_00000000_00000100;  //loadi 1     #4
        {instr_mem[10'd15], instr_mem[10'd14], instr_mem[10'd13], instr_mem[10'd12]}    = 32'b00000000_00000001_00000000_00001010;  //loadi 1     #10  
        {instr_mem[10'd19], instr_mem[10'd18], instr_mem[10'd17], instr_mem[10'd16]}    = 32'b00000111_00000001_00000001_00000000;  //beq   #1  1  0
        {instr_mem[10'd23], instr_mem[10'd22], instr_mem[10'd21], instr_mem[10'd20]}    = 32'b00000000_00000010_00000000_00001001;  //loadi 2     #9
        {instr_mem[10'd27], instr_mem[10'd26], instr_mem[10'd25], instr_mem[10'd24]}    = 32'b00000111_00000001_00000010_00000000;  //beq   #1  2  0
        {instr_mem[10'd31], instr_mem[10'd30], instr_mem[10'd29], instr_mem[10'd28]}    = 32'b00000011_00000011_00000000_00000001;  //sub   3   0  1
        {instr_mem[10'd35], instr_mem[10'd34], instr_mem[10'd33], instr_mem[10'd32]}    = 32'b00000010_00000011_00000000_00000001;  //add   3   0  1
        {instr_mem[10'd39], instr_mem[10'd38], instr_mem[10'd37], instr_mem[10'd36]}    = 32'b00001001_00000100_00000001_00000010;  //srl   4   1  #2   
        {instr_mem[10'd43], instr_mem[10'd42], instr_mem[10'd41], instr_mem[10'd40]}    = 32'b00001010_00000101_00000010_00000010;  //sra   5   2  #2   
        {instr_mem[10'd47], instr_mem[10'd46], instr_mem[10'd45], instr_mem[10'd44]}    = 32'b00001011_00000001_00000100_00000011;  //bne   #1  4  3
        {instr_mem[10'd51], instr_mem[10'd50], instr_mem[10'd49], instr_mem[10'd48]}    = 32'b00000000_00000110_00000000_00000011;  //loadi 6      #3
        {instr_mem[10'd55], instr_mem[10'd54], instr_mem[10'd53], instr_mem[10'd52]}    = 32'b00000000_00000111_00000000_00001000;  //loadi 7      #8
        {instr_mem[10'd59], instr_mem[10'd58], instr_mem[10'd57], instr_mem[10'd56]}    = 32'b00001100_00000111_00000010_00000011;  //ror   7   2  #3 
    end
    
    /* 
    -----
     CPU
    -----
    */
    cpu mycpu(PC, INSTRUCTION, CLK, RESET);

    initial
    begin
    
        // generate files needed to plot the waveform using GTKWave
        $dumpfile("cpu_wavedata.vcd");
		$dumpvars(0, cpu_tb, cpu_tb.mycpu.REGISTER.register[0], cpu_tb.mycpu.REGISTER.register[1], cpu_tb.mycpu.REGISTER.register[2], cpu_tb.mycpu.REGISTER.register[3], cpu_tb.mycpu.REGISTER.register[4], cpu_tb.mycpu.REGISTER.register[5], cpu_tb.mycpu.REGISTER.register[6], cpu_tb.mycpu.REGISTER.register[7]);
        
        CLK = 1'b0;
        RESET = 1'b0;
        
        // TODO: Reset the CPU (by giving a pulse to RESET signal) to start the program execution
        #2
        RESET = 1'b1;

        #4
        RESET= 1'b0;
        
        // finish simulation after some time
        #500
        $finish;
        
    end
    
    // clock signal generation
    always
        #4 CLK = ~CLK;
endmodule


//cpu module
module cpu(PC, INSTRUCTION, CLK, RESET);
    //Port&wire declarations
    input [31:0] INSTRUCTION;
    input RESET, CLK;
    output reg [31:0] PC;
    reg [2:0] ALU_SELECT;
    wire [7:0] OPERAND1,OPERAND2,RESULT,MUX1OUT,MUX2OUT;
    reg [7:0] twosComplement ,IMMEDIATE, JUMPCOUNT, OPCODE;
    reg [2:0] SOURCE1ADDRESS,SOURCE2ADDRESS,DESTINATIONADDRESS;
    reg WRITE, isSUBSTRACT, isIMMEDIATE, isJUMP, isBEQ, isBNE, isRIGHTSHIFT;
    wire [31:0] PCPLUSFOUR, NEXTPC, PCJUMP, EXTENDEDJUMPCOUNT, FINALJUMPCOUNT;
    wire ZERO;

    //get the increased PC value (+4)
    next_PC NEXTPCVAl(PC, PCPLUSFOUR);
    //directs the operand2 value if addition else directs the 2's complement value if substraction
    mux MUX1(twosComplement, OPERAND2, isSUBSTRACT, MUX1OUT);
    //directs the immediate value if operand2 is an immediate value else directs the MUX1OUT
    mux MUX2(IMMEDIATE, MUX1OUT, isIMMEDIATE, MUX2OUT);
    //Assign PC to the address of subsequent instruction or jump to another instruction
    mux_pc MUX3(PCJUMP, PCPLUSFOUR, isJUMP, isBEQ, isBNE, ZERO, NEXTPC);
    //Register file to store and retrieve data and results
    reg_file REGISTER(RESULT,OPERAND1,OPERAND2,DESTINATIONADDRESS,SOURCE1ADDRESS,SOURCE2ADDRESS,WRITE,CLK,RESET);
    //do ALU operations according to the ALU_SELECT value derived from OPCODE
    alu ALU(OPERAND1, MUX2OUT, RESULT, ALU_SELECT, ZERO, isRIGHTSHIFT);
    //Extend the offset to 32 bits
    extend EXTENDOFFSET(JUMPCOUNT, EXTENDEDJUMPCOUNT);
    //getting the offset value by multiplying the no of instructions to be jumped by 4
    shift SHIFT(EXTENDEDJUMPCOUNT, FINALJUMPCOUNT);
    //get the target address for j, beq instructions
    jump JUMPTO(PCPLUSFOUR, PCJUMP, FINALJUMPCOUNT);       


    //If reset=1 set the PC value to 0 synchronously with a delay of 1
    always @(posedge CLK) begin
        #1
        if(RESET) PC <= 32'd0; 
    end
    //Increase the PC value by for and assign it to the same PC synchronously with a delay of 1
    always @(posedge CLK) begin
        #1
        PC <= NEXTPC;
    end
    //Results the 2's complement value of OPERAND2
    always @(OPERAND2) begin
        #1 twosComplement = ~(OPERAND2)+1;        
    end

    //Instruction fetching mechanism
    always @(INSTRUCTION) begin
        OPCODE = INSTRUCTION[31:24];
        DESTINATIONADDRESS = INSTRUCTION[18:16];
        SOURCE1ADDRESS = INSTRUCTION[10:8];
        SOURCE2ADDRESS = INSTRUCTION[2:0];
        IMMEDIATE = INSTRUCTION[7:0];
        JUMPCOUNT = INSTRUCTION[23:16];

        #1
        case(OPCODE)
            // LOAD
            8'd0 : 
                begin
                    isSUBSTRACT = 1'b0;
                    isIMMEDIATE = 1'b1;
                    isJUMP = 1'b0;
                    isBEQ = 1'b0;
                    isBNE = 1'b0;
                    ALU_SELECT = 3'b000;
                    WRITE = 1;
                end
            // MOV
            8'd1 : 
                begin
                    isSUBSTRACT = 1'b0;
                    isIMMEDIATE = 1'b0;
                    isJUMP = 1'b0;
                    isBEQ = 1'b0;
                    isBNE = 1'b0;
                    ALU_SELECT = 3'b000;
                    WRITE = 1;
                end
            // ADD
            8'd2 : 
                begin
                    isSUBSTRACT = 1'b0;
                    isIMMEDIATE = 1'b0;
                    isJUMP = 1'b0;
                    isBEQ = 1'b0;
                    isBNE = 1'b0;
                    ALU_SELECT = 3'b001;
                    WRITE = 1;
                end
            // SUB
            8'd3 : 
                begin
                    isSUBSTRACT = 1'b1;
                    isIMMEDIATE = 1'b0;
                    isJUMP = 1'b0;
                    isBEQ = 1'b0;
                    isBNE = 1'b0;
                    ALU_SELECT = 3'b001;
                    WRITE = 1;
                end
            // AND
            8'd4 : 
                begin
                    isSUBSTRACT = 1'b0;
                    isIMMEDIATE = 1'b0;
                    isJUMP = 1'b0;
                    isBEQ = 1'b0;
                    isBNE = 1'b0;
                    ALU_SELECT = 3'b010;
                    WRITE = 1;
                end
            // OR
            8'd5 : 
                begin
                    isSUBSTRACT = 1'b0;
                    isIMMEDIATE = 1'b0;
                    isJUMP = 1'b0;
                    isBEQ = 1'b0;
                    isBNE = 1'b0;
                    ALU_SELECT = 3'b011;
                    WRITE = 1;
                end
            //j
            8'd6 :
                begin
                    isSUBSTRACT = 1'b0;
                    isIMMEDIATE = 1'b0;
                    isJUMP = 1'b1;
                    isBEQ = 1'b0;
                    isBNE = 1'b0;
                    WRITE = 0;
                end
            //beq
            8'd7 :
                begin
                    isSUBSTRACT = 1'b1;
                    isIMMEDIATE = 1'b0;
                    isJUMP = 1'b0;
                    isBEQ = 1'b1;
                    isBNE = 1'b0;
                    ALU_SELECT = 3'b001;
                    WRITE = 0;
                end
            //sll
            8'd8 :
                begin
                    isSUBSTRACT = 1'b0;
                    isIMMEDIATE = 1'b1;
                    isJUMP = 1'b0;
                    isBEQ = 1'b0;
                    isBNE = 1'b0;
                    ALU_SELECT = 3'b100;
                    isRIGHTSHIFT = 1'b0;
                    WRITE = 1;
                    
                end
            //srl
            8'd9 :
                begin
                    isSUBSTRACT = 1'b0;
                    isIMMEDIATE = 1'b1;
                    isJUMP = 1'b0;
                    isBEQ = 1'b0;
                    isBNE = 1'b0;
                    ALU_SELECT = 3'b100;
                    isRIGHTSHIFT = 1'b1;
                    WRITE = 1;
                    
                end
            //sra
            8'd10 :
                begin
                    isSUBSTRACT = 1'b0;
                    isIMMEDIATE = 1'b1;
                    isJUMP = 1'b0;
                    isBEQ = 1'b0;
                    isBNE = 1'b0;
                    ALU_SELECT = 3'b101;
                    WRITE = 1;
                end
            //bne
            8'd11 :
                begin
                    isSUBSTRACT = 1'b1;
                    isIMMEDIATE = 1'b0;
                    isJUMP = 1'b0;
                    isBEQ = 1'b0;
                    isBNE = 1'b1;
                    ALU_SELECT = 3'b001;
                    WRITE = 0;
                end
            //ror
            8'd12 :
                begin
                    isSUBSTRACT = 1'b0;
                    isIMMEDIATE = 1'b1;
                    isJUMP = 1'b0;
                    isBEQ = 1'b0;
                    isBNE = 1'b0;
                    ALU_SELECT = 3'b110;
                    WRITE = 1;
                end
        endcase
    end
endmodule

//MUX module
module mux(DATA1,DATA2,SELECT,OUTPUT);
    //Declaration of ports
    input [7:0] DATA1,DATA2;
    input SELECT;
    output reg [7:0] OUTPUT;

    //direct on of the data to the output according to the select value
    always@(*) begin
        case(SELECT)
            1'b1: OUTPUT <= DATA1;
            1'b0: OUTPUT <= DATA2;
            default: OUTPUT <= 8'd0;
        endcase
    end
endmodule

//MUX module for jump and branch instructions
module mux_pc(DATA1,DATA2,JUMPSELECT,BEQSELECT,BNESELECT,ZEROSELECT,OUTPUT);
    //Declaration of ports
    input [31:0] DATA1,DATA2;
    input JUMPSELECT, BEQSELECT, BNESELECT, ZEROSELECT;
    output reg [31:0] OUTPUT;

    //direct on of the data to the output according to the select value
    always@(*) begin
        if (JUMPSELECT) begin
            OUTPUT = DATA1;                         //If the instruction is j, assign the NextPC value to the target address
        end else if (BEQSELECT && ZEROSELECT) begin //If the instruction is beq and equal condition is satisfied,
            OUTPUT = DATA1;                         // assign the NextPC value to the target address
        end else if (BNESELECT && !ZEROSELECT) begin    //If the instruction is bne and notequal condition is satisfied
            OUTPUT = DATA1;                             // assign the NextPC value to the target address
        end else begin                              
            OUTPUT = DATA2;                         //Else nextPC value is increased by 4 from currentPC value
        end
        
    end
endmodule

//Next PC module
module next_PC(IN,OUT);
    input [31:0] IN;
    output reg [31:0] OUT;

    always@(IN) begin
        #1 OUT <= IN + 32'b100;  //increases the PC value by 4
    end
endmodule

//JUMP module for j , beq instructions
module jump(CURRENTPC, TARGETPC, JUMPBY);
    input [31:0] CURRENTPC, JUMPBY;
    output wire [31:0] TARGETPC;

    assign #2 TARGETPC = CURRENTPC + JUMPBY;   //Calculate the target address
endmodule

//Sign extend the offset value from 8 bits to 32 bits
module extend(OFFSET, EXTENDEDOFFSET);
    input [7:0] OFFSET;
    output reg [31:0] EXTENDEDOFFSET;

    always @(OFFSET) begin
        EXTENDEDOFFSET [7:0] = OFFSET;
        if (OFFSET[7]) begin
            EXTENDEDOFFSET [31:8] = 24'b111111111111111111111111;   //append 1's if MSB is 1
        end else begin
            EXTENDEDOFFSET [31:8] = 24'b000000000000000000000000;   //append 0's if MSB is 0
        end
    end
endmodule

//Shift module to shift the input number left by 2
module shift(VALUE, SHIFTEDVALUE);
    input signed [31:0] VALUE;
    output signed [31:0] SHIFTEDVALUE;

    assign SHIFTEDVALUE = VALUE<<2; //Left shift by 2 bits (mutiply by 4)
endmodule

Lab5/cpu_wavedata.vcd
$date
	Fri Jun 09 08:53:15 2023
$end
$version
	Icarus Verilog
$end
$timescale
	1s
$end
$scope module cpu_tb $end
$var wire 32 ! PC [31:0] $end
$var reg 1 " CLK $end
$var reg 32 # INSTRUCTION [31:0] $end
$var reg 1 $ RESET $end
$scope module mycpu $end
$var wire 1 " CLK $end
$var wire 32 % INSTRUCTION [31:0] $end
$var wire 1 $ RESET $end
$var wire 1 & ZERO $end
$var wire 8 ' RESULT [7:0] $end
$var wire 32 ( PCPLUSFOUR [31:0] $end
$var wire 32 ) PCJUMP [31:0] $end
$var wire 8 * OPERAND2 [7:0] $end
$var wire 8 + OPERAND1 [7:0] $end
$var wire 32 , NEXTPC [31:0] $end
$var wire 8 - MUX2OUT [7:0] $end
$var wire 8 . MUX1OUT [7:0] $end
$var wire 32 / FINALJUMPCOUNT [31:0] $end
$var wire 32 0 EXTENDEDJUMPCOUNT [31:0] $end
$var reg 3 1 ALU_SELECT [2:0] $end
$var reg 3 2 DESTINATIONADDRESS [2:0] $end
$var reg 8 3 IMMEDIATE [7:0] $end
$var reg 8 4 JUMPCOUNT [7:0] $end
$var reg 8 5 OPCODE [7:0] $end
$var reg 32 6 PC [31:0] $end
$var reg 3 7 SOURCE1ADDRESS [2:0] $end
$var reg 3 8 SOURCE2ADDRESS [2:0] $end
$var reg 1 9 WRITE $end
$var reg 1 : isBEQ $end
$var reg 1 ; isBNE $end
$var reg 1 < isIMMEDIATE $end
$var reg 1 = isJUMP $end
$var reg 1 > isRIGHTSHIFT $end
$var reg 1 ? isSUBSTRACT $end
$var reg 8 @ twosComplement [7:0] $end
$scope module ALU $end
$var wire 3 A SELECT [2:0] $end
$var wire 1 > SHIFTINDICATOR $end
$var wire 8 B Rotate [7:0] $end
$var wire 8 C Or [7:0] $end
$var wire 8 D LogicalShift [7:0] $end
$var wire 8 E Fwd [7:0] $end
$var wire 8 F DATA2 [7:0] $end
$var wire 8 G DATA1 [7:0] $end
$var wire 8 H ArithmeticShift [7:0] $end
$var wire 8 I And [7:0] $end
$var wire 8 J Add [7:0] $end
$var reg 8 K RESULT [7:0] $end
$var reg 1 & ZERO $end
$var reg 1 L zero_flag $end
$scope module Add_ $end
$var wire 8 M DATA2 [7:0] $end
$var wire 8 N DATA1 [7:0] $end
$var reg 8 O RESULT [7:0] $end
$upscope $end
$scope module And_ $end
$var wire 8 P DATA2 [7:0] $end
$var wire 8 Q DATA1 [7:0] $end
$var reg 8 R RESULT [7:0] $end
$upscope $end
$scope module ArithmeticShift_ $end
$var wire 8 S SHIFTAMOUNT [7:0] $end
$var wire 8 T OPERAND [7:0] $end
$var reg 8 U RESULT [7:0] $end
$var reg 7 V temp [6:0] $end
$var reg 8 W tempOperand [7:0] $end
$var integer 32 X j [31:0] $end
$upscope $end
$scope module Forward_ $end
$var wire 8 Y DATA2 [7:0] $end
$var reg 8 Z RESULT [7:0] $end
$upscope $end
$scope module LogicalShift_ $end
$var wire 1 > SHIFTSIDE $end
$var wire 8 [ SHIFTAMOUNT [7:0] $end
$var wire 8 \ OPERAND [7:0] $end
$var reg 8 ] RESULT [7:0] $end
$var reg 7 ^ temp [6:0] $end
$var reg 8 _ tempOperand [7:0] $end
$var integer 32 ` i [31:0] $end
$upscope $end
$scope module Or_ $end
$var wire 8 a DATA2 [7:0] $end
$var wire 8 b DATA1 [7:0] $end
$var reg 8 c RESULT [7:0] $end
$upscope $end
$scope module Rotate_ $end
$var wire 8 d ROTATEAMOUNT [7:0] $end
$var wire 8 e OPERAND [7:0] $end
$var reg 8 f RESULT [7:0] $end
$var reg 7 g temp [6:0] $end
$var reg 1 h tempLSB $end
$var reg 8 i tempOperand [7:0] $end
$var integer 32 j k [31:0] $end
$upscope $end
$upscope $end
$scope module EXTENDOFFSET $end
$var wire 8 k OFFSET [7:0] $end
$var reg 32 l EXTENDEDOFFSET [31:0] $end
$upscope $end
$scope module JUMPTO $end
$var wire 32 m TARGETPC [31:0] $end
$var wire 32 n JUMPBY [31:0] $end
$var wire 32 o CURRENTPC [31:0] $end
$upscope $end
$scope module MUX1 $end
$var wire 8 p DATA1 [7:0] $end
$var wire 1 ? SELECT $end
$var wire 8 q DATA2 [7:0] $end
$var reg 8 r OUTPUT [7:0] $end
$upscope $end
$scope module MUX2 $end
$var wire 8 s DATA1 [7:0] $end
$var wire 8 t DATA2 [7:0] $end
$var wire 1 < SELECT $end
$var reg 8 u OUTPUT [7:0] $end
$upscope $end
$scope module MUX3 $end
$var wire 1 : BEQSELECT $end
$var wire 1 ; BNESELECT $end
$var wire 32 v DATA1 [31:0] $end
$var wire 1 = JUMPSELECT $end
$var wire 1 & ZEROSELECT $end
$var wire 32 w DATA2 [31:0] $end
$var reg 32 x OUTPUT [31:0] $end
$upscope $end
$scope module NEXTPCVAl $end
$var wire 32 y IN [31:0] $end
$var reg 32 z OUT [31:0] $end
$upscope $end
$scope module REGISTER $end
$var wire 1 " CLK $end
$var wire 8 { IN [7:0] $end
$var wire 3 | INADDRESS [2:0] $end
$var wire 8 } OUT1 [7:0] $end
$var wire 3 ~ OUT1ADDRESS [2:0] $end
$var wire 8 !" OUT2 [7:0] $end
$var wire 3 "" OUT2ADDRESS [2:0] $end
$var wire 1 $ RESET $end
$var wire 1 9 WRITE $end
$var integer 32 #" i [31:0] $end
$upscope $end
$scope module SHIFT $end
$var wire 32 $" VALUE [31:0] $end
$var wire 32 %" SHIFTEDVALUE [31:0] $end
$upscope $end
$upscope $end
$upscope $end
$scope module cpu_tb $end
$scope module mycpu $end
$scope module REGISTER $end
$var reg 8 &" \register[0] [7:0] $end
$upscope $end
$upscope $end
$upscope $end
$scope module cpu_tb $end
$scope module mycpu $end
$scope module REGISTER $end
$var reg 8 '" \register[1] [7:0] $end
$upscope $end
$upscope $end
$upscope $end
$scope module cpu_tb $end
$scope module mycpu $end
$scope module REGISTER $end
$var reg 8 (" \register[2] [7:0] $end
$upscope $end
$upscope $end
$upscope $end
$scope module cpu_tb $end
$scope module mycpu $end
$scope module REGISTER $end
$var reg 8 )" \register[3] [7:0] $end
$upscope $end
$upscope $end
$upscope $end
$scope module cpu_tb $end
$scope module mycpu $end
$scope module REGISTER $end
$var reg 8 *" \register[4] [7:0] $end
$upscope $end
$upscope $end
$upscope $end
$scope module cpu_tb $end
$scope module mycpu $end
$scope module REGISTER $end
$var reg 8 +" \register[5] [7:0] $end
$upscope $end
$upscope $end
$upscope $end
$scope module cpu_tb $end
$scope module mycpu $end
$scope module REGISTER $end
$var reg 8 ," \register[6] [7:0] $end
$upscope $end
$upscope $end
$upscope $end
$scope module cpu_tb $end
$scope module mycpu $end
$scope module REGISTER $end
$var reg 8 -" \register[7] [7:0] $end
$upscope $end
$upscope $end
$upscope $end
$enddefinitions $end
$comment Show the parameter values. $end
$dumpall
$end
#0
$dumpvars
bx -"
bx ,"
bx +"
bx *"
bx )"
bx ("
bx '"
bx &"
bx00 %"
bx $"
bx #"
bx ""
bx !"
bx ~
bx }
bx |
bx {
bx z
bx y
bx x
bx w
bx v
bx u
bx t
bx s
bx r
bx q
bx p
bx o
bx00 n
bx m
bx l
bx k
bx j
bx i
xh
bx g
bx f
bx e
bx d
bx c
bx b
bx a
bx `
bx _
bx ^
bx ]
bx \
bx [
bx Z
bx Y
bx X
bx W
bx V
bx U
bx T
bx S
bx R
bx Q
bx P
bx O
bx N
bx M
xL
bx K
bx J
bx I
bx H
bx G
bx F
bx E
bx D
bx C
bx B
bx A
bx @
x?
x>
x=
x<
x;
x:
x9
bx 8
bx 7
bx 6
bx 5
bx 4
bx 3
bx 2
bx 1
bx 0
bx00 /
bx .
bx -
bx ,
bx +
bx *
bx )
bx (
bx '
x&
bx %
0$
bx #
0"
bx !
$end
#2
1$
#4
1"
#5
b0 !
b0 6
b0 y
b0 -"
b0 ,"
b0 +"
b0 *"
b0 )"
b0 ("
b0 '"
b0 &"
b1000 #"
#6
b100 ,
b100 x
b100 (
b100 o
b100 w
b100 z
0$
#7
b0 -
b0 F
b0 M
b0 P
b0 S
b0 Y
b0 [
b0 a
b0 d
b0 u
b0 /
b0 n
b0 %"
b0 0
b0 l
b0 $"
b0 4
b0 k
b1001 3
b1001 s
b1 8
b1 ""
b0 7
b0 ~
b0 2
b0 |
b0 5
b1001 #
b1001 %
#8
b1001 -
b1001 F
b1001 M
b1001 P
b1001 S
b1001 Y
b1001 [
b1001 a
b1001 d
b1001 u
b0 '
b0 K
b0 {
0L
b1 j
b1 X
b1 `
b0 I
b0 R
b0 E
b0 Z
19
b0 1
b0 A
0;
0:
0=
1<
0?
0"
#9
b0 .
b0 r
b0 t
0&
b1001 '
b1001 K
b1001 {
b1001 C
b1001 c
b1010 `
b0 D
b0 ]
b0 ^
b0 _
b1010 X
b0 H
b0 U
b0 V
b0 W
b1010 j
b0 B
b0 f
b0 g
0h
b0 i
b1001 E
b1001 Z
b1001 J
b1001 O
b100 )
b100 m
b100 v
b0 *
b0 q
b0 !"
b0 +
b0 G
b0 N
b0 Q
b0 T
b0 \
b0 b
b0 e
b0 }
#10
b0 @
b0 p
#12
1"
#13
b100 !
b100 6
b100 y
b1001 &"
#14
b1000 ,
b1000 x
b1000 (
b1000 o
b1000 w
b1000 z
#15
b0 -
b0 F
b0 M
b0 P
b0 S
b0 Y
b0 [
b0 a
b0 d
b0 u
b100 /
b100 n
b100 %"
b1 0
b1 l
b1 $"
b1 4
b1 k
b0 3
b0 s
b0 8
b0 ""
b1 2
b1 |
b110 5
b110000000010000000000000000 #
b110000000010000000000000000 %
b1001 +
b1001 G
b1001 N
b1001 Q
b1001 T
b1001 \
b1001 b
b1001 e
b1001 }
#16
b0 '
b0 K
b0 {
b100 ,
b100 x
b0 E
b0 Z
09
1=
0<
b1 j
1h
b1001 i
b1 X
b1001 W
b1 `
b1001 _
0"
